llama_index/tools/wikipedia/__init__.py
llama_index/tools/wikipedia/base.py
llama_index_tools_wikipedia-0.4.1.dist-info/METADATA
llama_index_tools_wikipedia-0.4.1.dist-info/WHEEL
llama_index_tools_wikipedia-0.4.1.dist-info/licenses/LICENSE
llama_index_tools_wikipedia-0.4.1.dist-info/RECORD
